morley/Morley.py
morley/__init__.py
morley/ethalon.png
morley/gui.py
morley/logo.png
morley/main.py
morley/version.py
morley-0.0.6.1.dist-info/METADATA
morley-0.0.6.1.dist-info/WHEEL
morley-0.0.6.1.dist-info/entry_points.txt
morley-0.0.6.1.dist-info/top_level.txt
morley-0.0.6.1.dist-info/RECORD
